{
  "profile": {
    "name": "Nakul Tiruviluamala",
    "tagline": "Musician · Audio Engineer · Technologist · Educator",
    "avatar": "/avatar.jpg"
  },
  "categories": [
    {
      "title": "Music",
      "note": "Scattered across platforms by era and distribution type — plenty more to be released.",
      "links": [
        { "label": "YouTube", "url": "https://youtube.com/@TheSlyProfessor", "brand": "youtube",
          "description": "Original music, performances, and course lectures" },
        { "label": "SoundCloud", "url": "https://soundcloud.com/theslyprofessor", "brand": "soundcloud",
          "description": "Tracks, sketches, and works in progress" },
        { "label": "Apple Music", "url": "https://music.apple.com/us/artist/the-sly-professor/1608619209", "brand": "applemusic",
          "description": "Singles released as The Sly Professor" }
      ]
    },
    {
      "title": "Projects & Platforms",
      "links": [
        { "label": "Midimaze", "url": "https://midimaze.com", "brand": "website",
          "description": "Interactive music-education platform" },
        { "label": "ConvexCompose", "url": "https://convex.store", "brand": "website",
          "description": "A module contract for business-domain Convex Components" },
        { "label": "NNT Docs", "url": "https://nnt-docs.com", "brand": "website",
          "description": "Documentation for NNT, a music-notation language — huge thanks to the help of Fred Garbutt (avocadojesus)" }
      ]
    },
    {
      "title": "Studio & Work",
      "links": [
        { "label": "Southwestern Recording", "url": "https://southwesternrecording.com", "brand": "website",
          "description": "The recording studio at Southwestern College, where I teach" },
        { "label": "Build Forward Tech", "url": "https://buildforwardtech.com", "brand": "website",
          "description": "Technology curation, consulting, and sector intelligence" }
      ]
    },
    {
      "title": "Connect",
      "links": [
        { "label": "Instagram", "url": "https://instagram.com/theslyprofessor", "brand": "instagram",
          "description": "Studio life and what I'm working on" },
        { "label": "LinkedIn", "url": "https://www.linkedin.com/in/theslyprofessor", "brand": "linkedin",
          "description": "Professional background and teaching" },
        { "label": "nakultiruviluamala.com", "url": "https://nakultiruviluamala.com", "brand": "website",
          "description": "Full bio, composition portfolio, and contact" }
      ]
    }
  ]
}
